my_test_api_client/__init__.py
my_test_api_client/api/__init__.py
my_test_api_client/api/tests/__init__.py
my_test_api_client/api/tests/defaults_tests_defaults_post.py
my_test_api_client/api/tests/get_basic_list_of_booleans.py
my_test_api_client/api/tests/get_basic_list_of_floats.py
my_test_api_client/api/tests/get_basic_list_of_integers.py
my_test_api_client/api/tests/get_basic_list_of_strings.py
my_test_api_client/api/tests/get_user_list.py
my_test_api_client/api/tests/int_enum_tests_int_enum_post.py
my_test_api_client/api/tests/json_body_tests_json_body_post.py
my_test_api_client/api/tests/no_response_tests_no_response_get.py
my_test_api_client/api/tests/octet_stream_tests_octet_stream_get.py
my_test_api_client/api/tests/optional_value_tests_optional_query_param.py
my_test_api_client/api/tests/test_inline_objects.py
my_test_api_client/api/tests/unsupported_content_tests_unsupported_content_get.py
my_test_api_client/api/tests/upload_file_tests_upload_post.py
my_test_api_client/client.py
my_test_api_client/models/__init__.py
my_test_api_client/models/a_model.py
my_test_api_client/models/an_enum.py
my_test_api_client/models/an_int_enum.py
my_test_api_client/models/body_upload_file_tests_upload_post.py
my_test_api_client/models/different_enum.py
my_test_api_client/models/free_form_model.py
my_test_api_client/models/http_validation_error.py
my_test_api_client/models/model_with_additional_properties_inlined.py
my_test_api_client/models/model_with_additional_properties_inlined_additional_property.py
my_test_api_client/models/model_with_additional_properties_refed.py
my_test_api_client/models/model_with_any_json_properties.py
my_test_api_client/models/model_with_any_json_properties_additional_property.py
my_test_api_client/models/model_with_primitive_additional_properties.py
my_test_api_client/models/model_with_primitive_additional_properties_a_date_holder.py
my_test_api_client/models/model_with_union_property.py
my_test_api_client-0.1.0.dist-info/WHEEL
my_test_api_client-0.1.0.dist-info/METADATA
my_test_api_client-0.1.0.dist-info/RECORD
